vrf_context/__init__.py
vrf_context/api/__init__.py
vrf_context/api/serializers.py
vrf_context/api/urls.py
vrf_context/api/views.py
vrf_context/filtersets.py
vrf_context/forms.py
vrf_context/migrations/0001_initial.py
vrf_context/migrations/__init__.py
vrf_context/models.py
vrf_context/navigation.py
vrf_context/tables.py
vrf_context/templates/vrf_context/vrfcontext.html
vrf_context/urls.py
vrf_context/views.py
netbox_vrf_context-0.1.0.dist-info/LICENSE
netbox_vrf_context-0.1.0.dist-info/WHEEL
netbox_vrf_context-0.1.0.dist-info/METADATA
netbox_vrf_context-0.1.0.dist-info/RECORD
