Metadata-Version: 2.1
Name: netbox-vrf-context
Version: 0.1.0
Summary: VRF Context plugin for Netbox
License: BSD-2-Clause
Author: The Hut Group
Requires-Python: >=3.10,<4.0
Classifier: License :: OSI Approved :: BSD License
Classifier: Programming Language :: Python :: 3
Classifier: Programming Language :: Python :: 3.10
Requires-Dist: netbox-bgp (>=0.7.0,<0.8.0)
Requires-Dist: netbox-static-routes-plugin (>=0.2,<0.3)
